pydexpi/__init__.py
pydexpi/dexpi_classes/__init__.py
pydexpi/dexpi_classes/customization.py
pydexpi/dexpi_classes/dataTypes.py
pydexpi/dexpi_classes/dexpiBaseModels.py
pydexpi/dexpi_classes/dexpiModel.py
pydexpi/dexpi_classes/enumerations.py
pydexpi/dexpi_classes/equipment.py
pydexpi/dexpi_classes/graphics.py
pydexpi/dexpi_classes/instrumentation.py
pydexpi/dexpi_classes/metaData.py
pydexpi/dexpi_classes/physicalQuantities.py
pydexpi/dexpi_classes/piping.py
pydexpi/dexpi_classes/plantStructure.py
pydexpi/dexpi_classes/pydantic_classes.py
pydexpi/loaders/__init__.py
pydexpi/loaders/graph_loader.py
pydexpi/loaders/json_serializer.py
pydexpi/loaders/ml_graph_loader.py
pydexpi/loaders/proteus_serializer.py
pydexpi/loaders/serializer.py
pydexpi/loaders/proteus_serializer/__init__.py
pydexpi/loaders/proteus_serializer/core.py
pydexpi/loaders/proteus_serializer/parser_factory.py
pydexpi/loaders/proteus_serializer/parser_modules.py
pydexpi/loaders/proteus_serializer/parsing_utils.py
pydexpi/loaders/proteus_serializer/proteus_serializer.py
pydexpi/syndata/__init__.py
pydexpi/syndata/connector_renaming.py
pydexpi/syndata/dexpi_pattern.py
pydexpi/syndata/generation_history.py
pydexpi/syndata/generator.py
pydexpi/syndata/generator_function.py
pydexpi/syndata/generator_step.py
pydexpi/syndata/graph_pattern.py
pydexpi/syndata/pattern.py
pydexpi/syndata/pattern_distribution.py
pydexpi/toolkits/__init__.py
pydexpi/toolkits/base_model_utils.py
pydexpi/toolkits/instrumentation_toolkit.py
pydexpi/toolkits/model_toolkit.py
pydexpi/toolkits/piping_toolkit.py
pydexpi-1.1.0.dist-info/METADATA
pydexpi-1.1.0.dist-info/WHEEL
pydexpi-1.1.0.dist-info/licenses/LICENSE
pydexpi-1.1.0.dist-info/RECORD
