Metadata-Version: 2.4
Name: pyDEXPI
Version: 1.1.0
Summary: Package containing the DEXPI data model in Python and a parser to load Proteus .xml data to the data model.
Project-URL: Homepage, https://www.pi-research.org/
Project-URL: Source, https://github.com/process-intelligence-research/pyDEXPI
Author-email: "Artur M. Schweidtmann" <A.Schweidtmann@tudelft.nl>, "Dominik P. Goldstein" <D.P.Goldstein@tudelft.nl>, Lukas Schulze Balhorn <L.Schulzebalhorn@tudelft.nl>, Achmad Anggawirya Alimin <A.Alimin@tudelft.nl>
License-File: LICENSE
Keywords: DEXPI, Proteus, P&ID
Classifier: License :: OSI Approved :: GNU Affero General Public License v3
Classifier: Operating System :: OS Independent
Classifier: Programming Language :: Python :: 3
Requires-Python: >=3.10
Requires-Dist: matplotlib>=3.8.4
Requires-Dist: networkx>=3.2.1
Requires-Dist: plotly>=5.24.1
Requires-Dist: pydantic>=2.11.7
Requires-Dist: sfiles2>=1.1.0
Provides-Extra: dev
Requires-Dist: pre-commit>=3.7.1; extra == 'dev'
Requires-Dist: pytest>=8.2.0; extra == 'dev'
Requires-Dist: ruff>=0.3.0; extra == 'dev'
